sas2sqlite3/__init__.py
sas2sqlite3/__main__.py
sas2sqlite3/adapters.py
sas2sqlite3-0.0.2.dist-info/LICENSE
sas2sqlite3-0.0.2.dist-info/METADATA
sas2sqlite3-0.0.2.dist-info/WHEEL
sas2sqlite3-0.0.2.dist-info/entry_points.txt
sas2sqlite3-0.0.2.dist-info/top_level.txt
sas2sqlite3-0.0.2.dist-info/RECORD
