Metadata-Version: 2.1
Name: sas2sqlite3
Version: 0.0.2
Summary: Import sas7bdat files to sqlite3 dbase
Home-page: https://github.com/ericgj/sas2sqlite.git
Author: Eric Gjertsen
Author-email: ericgj72@gmail.com
License: UNKNOWN
Platform: UNKNOWN
Classifier: Programming Language :: Python :: 3
Classifier: Operating System :: OS Independent
Classifier: Development Status :: 2 - Pre-Alpha
Classifier: License :: OSI Approved :: MIT License
Requires-Python: >=3.6
License-File: LICENSE
Requires-Dist: sas7bdat
Requires-Dist: julian
Provides-Extra: test
Requires-Dist: pytest ; extra == 'test'
